switch_package/__init__.py
switch_package-1.0.0.dist-info/METADATA
switch_package-1.0.0.dist-info/WHEEL
switch_package-1.0.0.dist-info/top_level.txt
switch_package-1.0.0.dist-info/RECORD
